odoo/addons/stock_picking_return_restricted_qty/README.rst
odoo/addons/stock_picking_return_restricted_qty/__init__.py
odoo/addons/stock_picking_return_restricted_qty/__manifest__.py
odoo/addons/stock_picking_return_restricted_qty/i18n/es.po
odoo/addons/stock_picking_return_restricted_qty/i18n/it.po
odoo/addons/stock_picking_return_restricted_qty/i18n/pt_BR.po
odoo/addons/stock_picking_return_restricted_qty/i18n/stock_picking_return_restricted_qty.pot
odoo/addons/stock_picking_return_restricted_qty/readme/CONTRIBUTORS.rst
odoo/addons/stock_picking_return_restricted_qty/readme/DESCRIPTION.rst
odoo/addons/stock_picking_return_restricted_qty/readme/USAGE.rst
odoo/addons/stock_picking_return_restricted_qty/static/description/icon.png
odoo/addons/stock_picking_return_restricted_qty/static/description/index.html
odoo/addons/stock_picking_return_restricted_qty/tests/__init__.py
odoo/addons/stock_picking_return_restricted_qty/tests/test_stock_picking_return_restricted_qty.py
odoo/addons/stock_picking_return_restricted_qty/wizard/__init__.py
odoo/addons/stock_picking_return_restricted_qty/wizard/stock_picking_return.py
odoo12_addon_stock_picking_return_restricted_qty-12.0.1.0.1.dist-info/METADATA
odoo12_addon_stock_picking_return_restricted_qty-12.0.1.0.1.dist-info/WHEEL
odoo12_addon_stock_picking_return_restricted_qty-12.0.1.0.1.dist-info/top_level.txt
odoo12_addon_stock_picking_return_restricted_qty-12.0.1.0.1.dist-info/RECORD
